{"member_organisations": "", "identification_number": "009940324183-42", "fields_of_interest": "General and Institutional Affairs, Economy, finance and the euro, Budget, International co-operation and development, Foreign and Security Policy and Defence, External Relations, Trans-European Networks, Borders and Security, Banking and financial services", "head_office_address": "Kingsfordweg 43-117", "full_time_equivalent_fte": "2,5", "person_with_legal_responsibility": "Stefan Bruggeman", "financial_year_start_date": "01/01/2016", "grants": "", "country_code": "NL", "head_office_country": "Netherlands", "eu_initiatives": "Ontwikkelingen die wij volgen op het gebied van:  \nMortgage Credit Directive \nConsumer Credit Directive \nEuropean Data Protection Directive", "level_of_interest": "global", "organisation_name": "Adaxio BV (Adaxio NL)", "belgium_office_post_code": "", "procurement": "", "section": "I - Professional consultancies/law firms/self-employed consultants", "lon": 4.8431787, "source": "", "belgium_office_address": "", "belgium_office_phone": "", "number_of_ep_accredited_persons": "", "overall_budget_turnover_as_a_range": "0-99999", "subsection": "Professional consultancies", "no_geo_reference": true, "persons_accredited_for_access_to_european_parliament_premises": "", "estimate_of_costs_absolute_amount": "", "registration_date": "28/10/2016", "website_address": "http://www.adaxio.nl", "commission_expert_groups_and_other_similar_entities_european_commission": "NA", "head_office_post_box": "37684", "head_office_city": "Amsterdam", "membership": "", "head_office_post_code": "1030 BH", "goals__remit": "Adaxio BV houdt zich bezig met het beheer van financi\u00eble producten.", "industry_forums": "", "inter_groups": "", "number_of_persons_involved": "10", "relevant_communication": "geen", "financial_year_end_date": "01/12/2016", "lat": 52.3864741, "estimate_of_costs_as_a_range": "50000-99999", "overall_budget_turnover_absolute_amount": "", "legal_status": "BV", "person_in_charge_of_eu_relations": "Jelle Wiersma", "customers": "", "belgium_office_post_box": "", "position": "Chief Legal Officer", "belgium_office_city": "", "head_office_phone": "(+31)882056800"}