{"member_organisations": "17 Colegios auton\u00f3micos de m\u00e9dicos \n52 colegios provinciales de m\u00e9dicos", "identification_number": "126815016642-71", "fields_of_interest": "Trade, Competition, Employment and Social Affairs, Environment, Single market, Public Health, Food Safety", "head_office_address": "Plaza de las Cortes, 11", "full_time_equivalent_fte": "2", "person_with_legal_responsibility": "Seraf\u00edn Romero Ag\u00fcit", "industry_forums": "", "grants": "", "country_code": "es", "inter_groups": "", "eu_initiatives": "Directiva Asistencia Transfronteriza \nDirectiva Reconocimiento de Calificaciones profesionales \nTratados de libre comercio \nAcceso Medicamentos  \nReglamento de protecci\u00f3n de datos y salud p\u00fablica \nRevisi\u00f3n EURES", "level_of_interest": "European, global, national", "organisation_name": "Consejo General de Colegios Oficiales de M\u00e9dicos (CGCOM)", "belgium_office_post_code": "", "number_of_persons_involved": "4", "person_in_charge_of_eu_relations": "Ricard Guti\u00e9rrez Mart\u00ed", "section": "VI - Organisations representing local, regional and municipal authorities, other public or mixed entities, etc.", "lon": "-3.6947086", "source": "", "subsection": "Other public or mixed entities, created by law whose purpose is to act in the public interest", "belgium_office_phone": "", "overall_budget_turnover_as_a_range": "", "belgium_office_address": "", "persons_accredited_for_access_to_european_parliament_premises": "", "registration_date": "18/03/2015", "estimate_of_costs_absolute_amount": "", "website_address": "http://www.cgcom.es", "commission_expert_groups_and_other_similar_entities_european_commission": "NA", "head_office_post_box": "", "head_office_city": "Madrid", "membership": "", "head_office_post_code": "", "position": "Delegado para Asuntos Europeos", "financial_year_start_date": "01/01/2017", "head_office_country": "Spain", "number_of_ep_accredited_persons": "", "relevant_communication": "Revisi\u00f3n de directiva asistencia transfronteriza \nAudiencias p\u00fablicas", "financial_year_end_date": "01/12/2017", "lat": "40.4152907", "estimate_of_costs_as_a_range": "100000-199999", "overall_budget_turnover_absolute_amount": "9000000", "legal_status": "corporaci\u00f3n de derecho p\u00fablico", "procurement": "", "customers": "", "belgium_office_post_box": "", "goals__remit": "Corresponde con car\u00e1cter general al CGCOM la representaci\u00f3n exclusiva, ordenaci\u00f3n y defensa de la profesi\u00f3n en el \u00e1mbito de todo el Estado, ostentando la representaci\u00f3n oficial de la OMC ante la Administraci\u00f3n General del Estado; la representaci\u00f3n de toda la profesi\u00f3n ante las organizaciones m\u00e9dicas y sanitarias internacionales; la representaci\u00f3n de la profesi\u00f3n m\u00e9dica ante las instituciones de la Uni\u00f3n Europea en aquellos temas que afecten al ejercicio profesional y a sus aspectos \u00e9ticos y deontol\u00f3gicos. \n \nFunciones \n \nEn particular el CGCOM tiene como funciones: \n \nTramitar las instancias o reclamaciones de los colegios oficiales de m\u00e9dicos dirigidas a los \u00f3rganos centrales de la Administraci\u00f3n General del Estado. \nPromover la mejora y perfeccionamiento de la legislaci\u00f3n sobre colegios profesionales. \nEstudiar los problemas de la profesi\u00f3n, proponiendo las reformas pertinentes, e intervenir en conflictos afecten a la Medicina. \nConocer y resolver los recursos que contra acuerdos de los Colegios Oficiales de M\u00e9dicos interpongan los colegiados. \nOstentar la representaci\u00f3n de los Colegios en la defensa de sus intereses profesionales. \nEjercer la potestad disciplinaria. \nEstablecer las normas de la \u00e9tica y de la deontolog\u00eda en el ejercicio de la profesi\u00f3n m\u00e9dica. \nCooperar para que la informaci\u00f3n y la publicidad relacionada con la profesi\u00f3n m\u00e9dica se ajuste a criterios profesionales. \nAdoptar las medidas necesarias para evitar la competencia desleal, velar por la dignidad y decoro del ejercicio profesional y denunciar el intrusismo y la clandestinidad. \nActualizar la competencia profesional de los m\u00e9dicos, promoviendo la Formaci\u00f3n M\u00e9dica Continuada y ejerciendo las funciones de acreditaci\u00f3n y registro oficial. \nEstablecer los criterios de colegiaci\u00f3n. \nCooperar con los poderes p\u00fablicos del Estado, en la formulaci\u00f3n de la pol\u00edtica sanitaria y de los planes asistenciales y en su ejecuci\u00f3n. \nExpedir a los colegiados las certificaciones que les sean requeridas por los pa\u00edses de la UE. \nOrganizar instituciones, servicios de asistencia y previsi\u00f3n. \nPromocionar y participar en la protecci\u00f3n social de los m\u00e9dicos jubilados e inv\u00e1lidos, viudas y hu\u00e9rfanos de m\u00e9dicos, casas de m\u00e9dicos o residencias, asistencia sanitaria, becas, ayudas y otras iniciativas similares. \nFormalizar los convenios de colaboraci\u00f3n que sean precisos para cumplir los fines de la organizaci\u00f3n. \nVelar por la b\u00fasqueda de nuevas salidas profesionales para los m\u00e9dicos. \nVelar por la homologaci\u00f3n y la equidad del ejercicio profesional. \nPromover la mejora de las condiciones del ejercicio profesional del m\u00e9dico. \nVelar porque el ejercicio de la profesi\u00f3n m\u00e9dica se adec\u00fae a los intereses de los ciudadanos. \nPromocionar el nivel cient\u00edfico, cultural, econ\u00f3mico y social de la profesi\u00f3n m\u00e9dica.", "belgium_office_city": "", "head_office_phone": "(+34)914317780"}