{"member_organisations": "https://www.tapaemea.org/membership/member-companies.html", "identification_number": "150999124671-53", "fields_of_interest": "Transport", "head_office_address": "TAPA EMEA Rhijngeesterstraatweg 40D", "full_time_equivalent_fte": "0,75", "person_with_legal_responsibility": "Laurence  Brown", "inter_groups": "", "financial_year_start_date": "01/01/2017", "grants": "", "head_office_country": "Netherlands", "eu_initiatives": "Unkown", "organisation_name": "Transported Asset Protection Association , Europe Middle East and Africa (TAPA EMEA)", "belgium_office_post_code": "", "number_of_persons_involved": "3", "procurement": "", "section": "II - In-house lobbyists and trade/business/professional associations", "source": "", "belgium_office_address": "", "subsection": "Trade and business associations", "belgium_office_phone": "", "number_of_ep_accredited_persons": "", "overall_budget_turnover_as_a_range": "", "belgium_office_city": "", "persons_accredited_for_access_to_european_parliament_premises": "", "estimate_of_costs_absolute_amount": "", "registration_date": "23/11/2016", "website_address": "http://www.tapaemea.org", "commission_expert_groups_and_other_similar_entities_european_commission": "Expert Group on Land Transport Security#E02821#http://ec.europa.eu/transparency/regexpert/index.cfm?do=groupDetail.groupDetail&groupID=2821#Observer#C", "head_office_post_box": "", "head_office_city": "Oegstgeest", "membership": "https://www.tapaemea.org/membership/member-companies.html", "head_office_post_code": "2341BV", "goals__remit": "TAPA's mission is to minimise cargo losses from the supply chain. TAPA achieves this through the development and application of global security standards, recognized industry practices, technology, education, benchmarking, regulatory collaboration, and the proactive identification of crime trends and supply chain security threats.", "industry_forums": "", "head_office_phone": "(+44)1633251325", "level_of_interest": "global", "relevant_communication": "", "financial_year_end_date": "01/12/2017", "estimate_of_costs_as_a_range": "0-9999", "overall_budget_turnover_absolute_amount": "0", "legal_status": "Association", "person_in_charge_of_eu_relations": "Laurence  Brown", "customers": "", "belgium_office_post_box": "", "position": "Executive Director"}