{"member_organisations": "http://www.theclimategroup.org/who-we-are/our-members/", "identification_number": "166412520967-61", "fields_of_interest": "Trade, Energy, Business and Industry, Environment, Single market, Research and innovation, Trans-European Networks, Transport, Climate Action", "head_office_address": "Second Floor, Riverside Building County Hall, Belvedere Road", "full_time_equivalent_fte": "0,5", "person_with_legal_responsibility": "Helen Clarkson", "financial_year_start_date": "01/07/2016", "grants": "", "country_code": "GB", "head_office_country": "United Kingdom", "eu_initiatives": "The Climate Group's main EU initiatives are EU climate and energy policy", "level_of_interest": "global", "organisation_name": "The Climate Group (UK registered name: The Climate Change Organisation)", "belgium_office_post_code": "", "procurement": "", "section": "III - Non-governmental organisations", "lon": -0.11864, "source": "", "belgium_office_address": "", "belgium_office_phone": "", "number_of_ep_accredited_persons": "", "overall_budget_turnover_as_a_range": "", "subsection": "Non-governmental organisations, platforms and networks and similar", "no_geo_reference": true, "persons_accredited_for_access_to_european_parliament_premises": "", "estimate_of_costs_absolute_amount": "", "registration_date": "29/03/2016", "website_address": "http://www.theclimategroup.org", "commission_expert_groups_and_other_similar_entities_european_commission": "NA", "head_office_post_box": "", "head_office_city": "London", "membership": "We Mean Business coalition \nIPCC (Observer Membership) \nUNFCCC (Observer Status)", "head_office_post_code": "SE1 7PB", "goals__remit": "TCG is an international non-profit bringing together powerful networks of businesses and governments, which shift global markets and policies, towards a world of under 2\u00b0C of global warming and greater prosperity for all, without delay. We act as a catalyst to take innovation and solutions to scale. And we use the power of communication to build ambition and pace, focusing on the greatest global opportunities for change. \n \nOur vision is a world of under 2\u00b0C of global warming and greater prosperity for all. \n \nOur mission is accelerating climate action.", "industry_forums": "", "inter_groups": "", "number_of_persons_involved": "2", "relevant_communication": "", "financial_year_end_date": "01/06/2017", "lat": 51.501485, "estimate_of_costs_as_a_range": "0-9999", "overall_budget_turnover_absolute_amount": "5544923", "legal_status": "charity", "person_in_charge_of_eu_relations": "Sam Kimmins", "customers": "", "belgium_office_post_box": "", "position": "Head of RE100", "belgium_office_city": "", "head_office_phone": "(+44)2079602970"}