{"member_organisations": "", "identification_number": "195167925116-12", "fields_of_interest": "Competition, Trans-European Networks, Transport, Climate Action", "head_office_address": "Dalsagervej 9", "full_time_equivalent_fte": "0,25", "person_with_legal_responsibility": "Morten Larsen", "inter_groups": "", "financial_year_start_date": "01/01/2016", "grants": "", "head_office_country": "Denmark", "eu_initiatives": "European Sustainable Shipping Forum \nLiquified Natural Gas \nCarbon Footprint \nMonitoring Reporting and Verification", "organisation_name": "Fjord Line", "belgium_office_post_code": "", "number_of_persons_involved": "1", "procurement": "", "section": "II - In-house lobbyists and trade/business/professional associations", "source": "", "belgium_office_address": "", "subsection": "Companies & groups", "belgium_office_phone": "", "number_of_ep_accredited_persons": "", "overall_budget_turnover_as_a_range": "", "belgium_office_city": "", "persons_accredited_for_access_to_european_parliament_premises": "", "estimate_of_costs_absolute_amount": "0", "registration_date": "16/12/2016", "website_address": "http://fjordline.com", "commission_expert_groups_and_other_similar_entities_european_commission": "NA", "head_office_post_box": "", "head_office_city": "Hirtshals", "membership": "", "head_office_post_code": "9850", "goals__remit": "To secure safe and sustainable shipping service, protect the environment and with equal competition.", "industry_forums": "", "head_office_phone": "(+45)97963000", "level_of_interest": "European", "relevant_communication": "", "financial_year_end_date": "01/12/2016", "estimate_of_costs_as_a_range": "", "overall_budget_turnover_absolute_amount": "0", "legal_status": "Ltd", "person_in_charge_of_eu_relations": "Morten Larsen", "customers": "", "belgium_office_post_box": "", "position": "Project Director"}