{"member_organisations": "", "identification_number": "279054921098-72", "fields_of_interest": "Agriculture, Energy, Environment, Research and innovation, Transport, Climate Action", "head_office_address": "Dennenboslaan 26", "full_time_equivalent_fte": "2,25", "person_with_legal_responsibility": "Simon Minett", "inter_groups": "", "financial_year_start_date": "01/01/2017", "grants": "25000", "head_office_country": "Belgium", "eu_initiatives": "Energy and environment policies \nCogeneration, District Heating and associated technologies \nClean transport \nEU ETS", "organisation_name": "Challoch Energy (Challoch)", "belgium_office_post_code": "", "number_of_persons_involved": "4", "procurement": "", "section": "I - Professional consultancies/law firms/self-employed consultants", "source": "", "belgium_office_address": "", "subsection": "Professional consultancies", "belgium_office_phone": "", "number_of_ep_accredited_persons": "", "overall_budget_turnover_as_a_range": "100000-499999", "belgium_office_city": "", "persons_accredited_for_access_to_european_parliament_premises": "", "estimate_of_costs_absolute_amount": "", "registration_date": "16/03/2016", "website_address": "http://www.challoch-energy.com", "commission_expert_groups_and_other_similar_entities_european_commission": "NA", "head_office_post_box": "", "head_office_city": "Overijse", "membership": "COGEN Europe", "head_office_post_code": "3090", "goals__remit": "Energy and Transport consulting practice, covering clean energy options. \nClients include Oil, gas, industrial companies, national and local authorities \nWork covers: technical engineering, policy monitoring, market development", "industry_forums": "", "head_office_phone": "(+32)26883232", "level_of_interest": "European", "relevant_communication": "Policy Managers to COGEN Europe \nAdvisers to Cefic on energy efficiency \nPower to Gas developments \nSmart grids \nITS and e-mobility \nBiochar and phosphorous recovery", "financial_year_end_date": "01/12/2017", "estimate_of_costs_as_a_range": "50000-99999", "overall_budget_turnover_absolute_amount": "", "legal_status": "BVBA", "person_in_charge_of_eu_relations": "Simon Minett", "customers": "", "belgium_office_post_box": "", "position": "Managing Director"}