{"member_organisations": "http://coordinadoraecoloxista.org/", "identification_number": "383780918753-22", "fields_of_interest": "Agriculture, Energy, Environment, Food Safety, Climate Action", "head_office_address": "C/Padre Teral 26-Q", "full_time_equivalent_fte": "0,5", "person_with_legal_responsibility": "Fructuoso Pontigo Concha", "financial_year_start_date": "01/01/2017", "grants": "", "country_code": "ES", "head_office_country": "Spain", "eu_initiatives": "Gesti\u00f3n de residuos \nGestion pesquera \nGesti\u00f3n forestal \nGestion LIFE \nGestion contaminaci\u00f3n del aire \nGesti\u00f3n uso trasgenicos", "level_of_interest": "global, regional/local", "organisation_name": "Coordinadora Ecoloxista d'Asturies (Coordina Ecoloxista)", "belgium_office_post_code": "", "procurement": "", "section": "III - Non-governmental organisations", "lon": -5.9171977, "source": "", "belgium_office_address": "", "belgium_office_phone": "", "number_of_ep_accredited_persons": "", "overall_budget_turnover_as_a_range": "", "subsection": "Non-governmental organisations, platforms and networks and similar", "no_geo_reference": true, "persons_accredited_for_access_to_european_parliament_premises": "", "estimate_of_costs_absolute_amount": "50", "registration_date": "11/09/2015", "website_address": "http://coordinadoraecoloxista.org/", "commission_expert_groups_and_other_similar_entities_european_commission": "NA", "head_office_post_box": "", "head_office_city": "Aviles", "membership": "", "head_office_post_code": "33403", "goals__remit": "Asociaci\u00f3n que trabaja los problemas ambientales de Asturias y los asociados a la calidad de vida de sus vecinos.", "industry_forums": "", "inter_groups": "", "number_of_persons_involved": "2", "relevant_communication": "Residuos \nAgricultura \nPesca \nSaneamiento \nGanaderia \nNaturaleza", "financial_year_end_date": "01/12/2017", "lat": 43.5398162, "estimate_of_costs_as_a_range": "", "overall_budget_turnover_absolute_amount": "4000", "legal_status": "Asociaci\u00f3n", "person_in_charge_of_eu_relations": "Fructuoso Pontigo Concha", "customers": "", "belgium_office_post_box": "", "position": "Presidente", "belgium_office_city": "", "head_office_phone": "(+34)629892624"}