{"member_organisations": "none", "identification_number": "41829078012-04", "fields_of_interest": "Education and training", "head_office_address": "Kando House Dublin 2", "full_time_equivalent_fte": "1", "person_with_legal_responsibility": "Professor Hardeep Singh Sandhu", "industry_forums": "", "grants": "180000", "inter_groups": "", "eu_initiatives": "education", "level_of_interest": "global", "organisation_name": "ISLES INTERNATIONAL UNIVERSITY (IIU)", "belgium_office_post_code": "", "number_of_persons_involved": "4", "person_in_charge_of_eu_relations": "Jean-Pierre  Poelmans", "section": "I - Professional consultancies/law firms/self-employed consultants", "source": "", "subsection": "Professional consultancies", "belgium_office_phone": "", "overall_budget_turnover_as_a_range": "", "belgium_office_address": "", "no_geo_reference": true, "persons_accredited_for_access_to_european_parliament_premises": "", "registration_date": "08/02/2012", "estimate_of_costs_absolute_amount": "", "website_address": "http://www.iiuedu.eu", "commission_expert_groups_and_other_similar_entities_european_commission": "NA", "head_office_post_box": "", "head_office_city": "Dublin", "membership": "Tuition Institutions which have received Recognition or been awarded Certification  \n \nLinks to academic institutions who granted permission to become included in executed collaboration agreement: \n \n \nAmerican Global University (USA) \nSchool of Medicine  \n8770 W Bryn Mawr Suite 1300  \nChicago, IL 60631  \nUnited States of America  \n \n \nEastern Asia University \n200 Rangsitnakhonnayok Road \nRangsit Thanyaburi Pathumthani \nThailand \n  \n \nUniversity of Management and Economics \nGround Floor, UME Building 47 \nPreak Preas Sdach, Battambang \nCambodia \n \n \nHanoi University of Agriculture \nTrau Quy - Gia Lam \nHa Noi \nVietnam \n \nKhulna University of Engineering & Technology \nKhulna University of Engineering and Technology \nKhulna-9203 \nBangladesh \n \nThe Southern University of Bangladesh \nInstitute of Management & Information Technology \n739/A Mehedibagh Road Chittagong \n \n  \nIBAIS (Institute of Business Administration and Information System) \nHouse # 57, Road # 12/A \nDhanmondi R/A,Dhaka -1209 \nBangladesh  \n \n \nNational University of Laos \nDongdok Campus, National University of Laos  \nP.O.Box:7322, Dongdok, Vientiane, Lao PDR.", "head_office_post_code": "2", "position": "Chairman", "financial_year_start_date": "01/01/2017", "head_office_country": "Ireland", "number_of_ep_accredited_persons": "", "relevant_communication": "education", "financial_year_end_date": "01/12/2017", "estimate_of_costs_as_a_range": "300000-399999", "overall_budget_turnover_absolute_amount": "100000", "legal_status": "private university", "procurement": "", "customers": "OXBRIDGE PROJECT", "belgium_office_post_box": "", "goals__remit": "Mission \n \nAfter almost one and half decades of becoming established as the first independent non-for-profit university in Europe and being today a self governed community of scholars, the Isles Internationale Universit\u00e9 (European Union) has been appointed to host the School of Doctoral Studies (EU) in Brussels, Belgium, and has been commanded to accomplish three fundamental missions: \n \n1.Development and enhancement of elite doctoral studies\u2019 programmes, with highest worldwide standards on academic and scientific cutting-edge research; \n \n2.Enforcement of EU analogue quality standards on academic programmes developed by tuition institutions outside the EU area: (a) By evaluating academic methodology applied on learning programmes; (b) By providing full coaching and tutoring support to tuition institutions worldwide to upgrade, assure and maintain academic methodology quality levels on their way towards excellence; and (3) By awarding EUASC Seal (EU Analogue Standards Certification) at corresponding quality levels achieved at each evaluation point; and \n \n3.Ensuring  academic EU Analogue Standards by performing: (a) Academic Validation on degrees earned by students at recognised and/or certified tuition institutions located outside the EU area; (b) Double Degree awarding on degrees earned by students at recognised and/or certified tuition institutions located elsewhere the EU area; and (c) Degrees awarding on studies programmes developed by tuition institutions, once certification at higher quality levels on applied academic methodology is granted and after collaboration agreement has been executed for these purposes . \n \nIn order to achieve its missions, the Universit\u00e9 has gathered some of the best minds in Europe, who have developed sate-of-the-art doctoral academic programmes, elite research and academic methodology, and cutting-edge technological tools, acting as permanent Staff and Faculty Members to strictly enforce this toolkit\u2019s proper application on daily basis.", "belgium_office_city": "", "head_office_phone": "(+6019)2122999"}