{"member_organisations": "", "identification_number": "485329315341-81", "fields_of_interest": "General and Institutional Affairs, Competition, International co-operation and development, Environment, Taxation, Single market, Trans-European Networks, Transport, Banking and financial services, Migration and asylum", "head_office_address": "Valletta Waterfront, Vault 13", "full_time_equivalent_fte": "0,25", "person_with_legal_responsibility": "Tonio Ellul", "financial_year_start_date": "01/01/2017", "grants": "", "country_code": "MT", "head_office_country": "Malta", "eu_initiatives": "Aviation \nShipping \nTaxation \nTelecommunications \nCompetition Law \niGaming \nDevelopment", "level_of_interest": "European, global, national", "organisation_name": "EMD Advisory Services (EMD)", "belgium_office_post_code": "", "procurement": "", "section": "I - Professional consultancies/law firms/self-employed consultants", "lon": 14.5079854, "source": "", "belgium_office_address": "", "belgium_office_phone": "", "number_of_ep_accredited_persons": "", "overall_budget_turnover_as_a_range": "0-99999", "subsection": "Professional consultancies", "no_geo_reference": true, "persons_accredited_for_access_to_european_parliament_premises": "", "estimate_of_costs_absolute_amount": "", "registration_date": "19/12/2014", "website_address": "http://www.emd.com.mt", "commission_expert_groups_and_other_similar_entities_european_commission": "NA", "head_office_post_box": "", "head_office_city": "Floriana", "membership": "TELFA - Trans-European Law Firm Alliance", "head_office_post_code": "FRN1914", "goals__remit": "EMD is an established multi-disciplinary firm based in Malta providing legal, tax, advisory and corporate services.", "industry_forums": "", "inter_groups": "", "number_of_persons_involved": "1", "relevant_communication": "", "financial_year_end_date": "01/12/2017", "lat": 35.8901301, "estimate_of_costs_as_a_range": "0-9999", "overall_budget_turnover_absolute_amount": "", "legal_status": "Company", "person_in_charge_of_eu_relations": "Tonio Ellul", "customers": "", "belgium_office_post_box": "", "position": "Director", "belgium_office_city": "", "head_office_phone": "(+356)22030000"}