{"member_organisations": "", "identification_number": "533559830559-85", "fields_of_interest": "Trade, Consumers, International co-operation and development, Single market, Research and innovation", "head_office_address": "Defreggerstra\u00dfe 35", "full_time_equivalent_fte": "0,25", "person_with_legal_responsibility": "Reinhold Maurer", "industry_forums": "", "grants": "", "country_code": "at", "inter_groups": "", "eu_initiatives": "Die Entwicklung europ\u00e4ischer Richtlinien, im besonderen die der Bauprodukteverordnung und der MAschinenrichtlinie wird derzeit beobachtet.", "level_of_interest": "regional/local", "organisation_name": "Ingenieurb\u00fcro Maurer R. (IBMR AT)", "belgium_office_post_code": "", "number_of_persons_involved": "1", "person_in_charge_of_eu_relations": "Reinhold Maurer", "section": "I - Professional consultancies/law firms/self-employed consultants", "lon": "11.4115972", "source": "", "subsection": "Self-employed consultants", "belgium_office_phone": "", "overall_budget_turnover_as_a_range": "", "belgium_office_address": "", "persons_accredited_for_access_to_european_parliament_premises": "", "registration_date": "06/03/2018", "estimate_of_costs_absolute_amount": "0", "website_address": "http://www.ibmr.at", "commission_expert_groups_and_other_similar_entities_european_commission": "NA", "head_office_post_box": "", "head_office_city": "Innsbruck", "membership": "DVGW \n\u00d6VGW \nDWA \nASI", "head_office_post_code": "6020", "position": "Inhaber", "financial_year_start_date": "", "head_office_country": "Austria", "number_of_ep_accredited_persons": "", "relevant_communication": "European standardization", "financial_year_end_date": "", "lat": "47.2657684", "estimate_of_costs_as_a_range": "", "overall_budget_turnover_absolute_amount": "0", "legal_status": "Einzelfirma", "procurement": "", "customers": "", "belgium_office_post_box": "", "goals__remit": "Beratung von Unternehmen in Bezug auf die europ\u00e4ischen Richtlinien und Einhaltung dieser bei Herstellung und Inverkehrbringen von Produkten.", "belgium_office_city": "", "head_office_phone": "(+43)6505341368"}