{"member_organisations": "", "identification_number": "636752920377-18", "fields_of_interest": "Budget, Research and innovation, Public Health", "head_office_address": "40 Wall Street 24th Floor", "full_time_equivalent_fte": "0,5", "person_with_legal_responsibility": "Mel Spigelman", "industry_forums": "", "grants": "", "inter_groups": "", "eu_initiatives": "Innovation for global health research and development primarily in Horizon2020 and FP9.", "level_of_interest": "global", "organisation_name": "Global Alliance for Tuberculosis Drug Development (TB Alliance)", "belgium_office_post_code": "1000", "number_of_persons_involved": "2", "person_in_charge_of_eu_relations": "Willo Brock", "section": "III - Non-governmental organisations", "source": "", "subsection": "Non-governmental organisations, platforms and networks and similar", "belgium_office_phone": "(+32)2 791 77 27", "overall_budget_turnover_as_a_range": "", "belgium_office_address": "Square De Meeus, 37", "no_geo_reference": true, "persons_accredited_for_access_to_european_parliament_premises": "BROCK#Willo, MORTON#Erin", "registration_date": "20/01/2016", "estimate_of_costs_absolute_amount": "", "website_address": "http://www.tballiance.org", "commission_expert_groups_and_other_similar_entities_european_commission": "NA", "head_office_post_box": "", "head_office_city": "New York", "membership": "", "head_office_post_code": "10005", "position": "Senior Vice President for External Affairs", "financial_year_start_date": "01/01/2016", "head_office_country": "United States", "number_of_ep_accredited_persons": "2", "relevant_communication": "World TB Day activities around innovation in TB research", "financial_year_end_date": "01/12/2016", "estimate_of_costs_as_a_range": "10000-24999", "overall_budget_turnover_absolute_amount": "53033369", "legal_status": "501(c)(3)", "procurement": "", "customers": "", "belgium_office_post_box": "", "goals__remit": "TB Alliance is a not-for-profit organization dedicated to the discovery and development of better, faster-acting, and affordable tuberculosis drugs that are available to those who need them.", "belgium_office_city": "Bruxelles", "head_office_phone": "(+1)2122277540"}