{"member_organisations": "", "identification_number": "789002115168-26", "fields_of_interest": "Economy, finance and the euro, Trade, Single market, Foreign and Security Policy and Defence", "head_office_address": "Frejgatan 13", "full_time_equivalent_fte": "7", "person_with_legal_responsibility": "Fredrik Erixon", "inter_groups": "", "financial_year_start_date": "01/01/2016", "grants": "", "head_office_country": "Sweden", "eu_initiatives": "Trade agreementsUppdraget \u00e4r att verka f\u00f6r mer policy-orienterad forskning i internationell politisk ekonomi och skapa en b\u00e4ttre kultur av utv\u00e4rdering i europeisk internationell politik.", "organisation_name": "European Centre for International Political Economy (ECIPE)", "belgium_office_post_code": "", "number_of_persons_involved": "7", "procurement": "", "section": "IV - Think tanks, research and academic institutions", "source": "", "belgium_office_address": "", "subsection": "Think tanks and research institutions", "belgium_office_phone": "", "number_of_ep_accredited_persons": "", "overall_budget_turnover_as_a_range": "", "belgium_office_city": "", "persons_accredited_for_access_to_european_parliament_premises": "", "estimate_of_costs_absolute_amount": "", "registration_date": "06/12/2014", "website_address": "http://www.ecipe.org", "commission_expert_groups_and_other_similar_entities_european_commission": "NA", "head_office_post_box": "576", "head_office_city": "Stockholm", "membership": "", "head_office_post_code": "114 79", "goals__remit": "Uppdraget \u00e4r att verka f\u00f6r mer policy-orienterad forskning i internationell politisk ekonomi och skapa en b\u00e4ttre kultur av utv\u00e4rdering i europeisk internationell politik.", "industry_forums": "", "head_office_phone": "(+46)709733683", "level_of_interest": "European", "relevant_communication": "", "financial_year_end_date": "01/12/2016", "estimate_of_costs_as_a_range": "0-9999", "overall_budget_turnover_absolute_amount": "900000", "legal_status": "Frivillig organisation", "person_in_charge_of_eu_relations": "Fredrik Erixon", "customers": "", "belgium_office_post_box": "", "position": "Chef"}