{"member_organisations": "", "identification_number": "830978625150-97", "fields_of_interest": "Education and training, Employment and Social Affairs, Youth", "head_office_address": "Wiedner Hauptstra\u00dfe 18", "full_time_equivalent_fte": "1", "person_with_legal_responsibility": "Stefan Humpl", "industry_forums": "", "grants": "", "country_code": "at", "inter_groups": "", "eu_initiatives": "ESCO - European Classification of Education, Skills, Competences and Occupations, EQF - European Qualification Framework, ECVET - European Credit System for Vocational Education and Training, Transparenzinstrumente im Bereich Berufsbildung", "level_of_interest": "European, global, national, regional/local", "organisation_name": "3s Unternehmensberatung GmbH (3s)", "belgium_office_post_code": "", "number_of_persons_involved": "4", "person_in_charge_of_eu_relations": "Stefan Humpl", "section": "I - Professional consultancies/law firms/self-employed consultants", "lon": "16.3672056", "source": "Erasmus+, Vergaben aus DG EMPL", "subsection": "Professional consultancies", "belgium_office_phone": "", "overall_budget_turnover_as_a_range": "0-99999", "belgium_office_address": "", "persons_accredited_for_access_to_european_parliament_premises": "", "registration_date": "19/12/2016", "estimate_of_costs_absolute_amount": "", "website_address": "http://www.3s.co.at", "commission_expert_groups_and_other_similar_entities_european_commission": "NA", "head_office_post_box": "", "head_office_city": "Wien", "membership": "Wirtschaftskammer \u00d6sterreich (http://www.wko.or.at)", "head_office_post_code": "1040", "position": "Gesch\u00e4ftsf\u00fchrer", "financial_year_start_date": "01/01/2016", "head_office_country": "Austria", "number_of_ep_accredited_persons": "", "relevant_communication": "Unterst\u00fctzung ESCO Sekretariat, Unterst\u00fctzung EQF Beirat, Unterst\u00fctzung ECVET Sekretariat", "financial_year_end_date": "01/12/2016", "lat": "48.1967828", "estimate_of_costs_as_a_range": "50000-99999", "overall_budget_turnover_absolute_amount": "", "legal_status": "Gesellschaft mit beschr\u00e4nkter Haftung", "procurement": "90000", "customers": "", "belgium_office_post_box": "", "goals__remit": "Forschung und Beratung in Berufs- und Hochschulbildung, Bildungspolitik, Transparenz von Berufsbildungsabschl\u00fcssen, Klassifikation von Berufen und Kompetenzen", "belgium_office_city": "", "head_office_phone": "(+43)15850915"}