{"member_organisations": "www.aenao.org", "identification_number": "89822835707-92", "fields_of_interest": "Culture and media, Culture, Education and training, Employment and Social Affairs, Environment, Youth, Justice and Fundamental Rights, Public Health, Digital economy and society, Sport", "head_office_address": "2, PANAGIA GOUMERA STR , PO BOX D 1436", "full_time_equivalent_fte": "1,25", "person_with_legal_responsibility": "AIKATERINI AMOUTZIA", "industry_forums": "", "grants": "91676", "inter_groups": "", "eu_initiatives": "H MKO AENAO \u03c5\u03bb\u03bf\u03c0\u03bf\u03b5\u03af \u03c0\u03c1\u03bf\u03b3\u03c1\u03ac\u03bc\u03bc\u03b1\u03c4\u03b1 \u03c3\u03c4\u03b1 \u03c0\u03bb\u03ac\u03b9\u03c3\u03b9\u03b1 \u03c4\u03bf\u03c5 ERASMUS+, \u03ba\u03b1\u03b9 \u03b5\u03c0\u03b9\u03ba\u03b5\u03bd\u03c4\u03c1\u03ce\u03bd\u03b5\u03c4\u03b1\u03b9 \u03c3\u03c4\u03b7 \u03ba\u03b9\u03bd\u03b7\u03c4\u03b9\u03ba\u03cc\u03c4\u03b7\u03c4\u03b1 \u03c4\u03c9\u03bd \u03bd\u03ad\u03c9\u03bd. \u03a9\u03c2 \u03ba\u03ad\u03bd\u03c4\u03c1\u03bf \u03bc\u03b7 \u03c4\u03c5\u03c0\u03b9\u03ba\u03ae\u03c2 \u03bc\u03ac\u03b8\u03b7\u03c3\u03b7\u03c2  \n- \u03c5\u03bb\u03bf\u03c0\u03bf\u03b9\u03b5\u03af \u03b2\u03b9\u03c9\u03bc\u03b1\u03c4\u03b9\u03ba\u03ad\u03c2 \u03b4\u03c1\u03ac\u03c3\u03b5\u03b9\u03c2 \u03c3\u03b5 \u03bd\u03ad\u03bf\u03c5\u03c2 \u03ba\u03b1\u03b9  \u03c3\u03b5 \u03bc\u03b1\u03b8\u03b7\u03c4\u03ad\u03c2 \u03b1\u03c0\u03cc \u03c7\u03ce\u03c1\u03b5\u03c2 \u03c4\u03b7\u03c2 \u0395.\u0395  \u03c3\u03b5 youth workes \u03b1\u03c0\u03cc \u0399\u03bd\u03b4\u03af\u03b1,\u039d\u03b5\u03c0\u03ac\u03bb, \u0392\u03b9\u03b5\u03c4\u03bd\u03ac\u03bc \u03ba\u03b1\u03b9 \u0395.\u0395 , \u03c0\u03b1\u03c1\u03b5\u03bc\u03b2\u03ac\u03c3\u03b5\u03b9\u03c2 \u03b3\u03b9\u03b1 \u03b5\u03bd\u03c3\u03c9\u03bc\u03ac\u03c4\u03c9\u03c3\u03b7 \u03c0\u03c1\u03bf\u03c3\u03c6\u03cd\u03b3\u03c9\u03bd \n- \u03c3\u03c5\u03bc\u03bc\u03b5\u03c4\u03ad\u03c7\u03b5\u03b9 \u03c3\u03b5 \u03c0\u03b1\u03c1\u03b1\u03b3\u03c9\u03b3\u03ae \u03b5\u03b3\u03c7\u03b5\u03b9\u03c1\u03b9\u03b4\u03af\u03bf\u03c5 \u03bc\u03b7 \u03c4\u03c5\u03c0\u03b9\u03ba\u03ae\u03c2 \u03bc\u03ac\u03b8\u03b7\u03c3\u03b7\u03c2, \u03b1\u03c0\u03b5\u03c5\u03b8\u03c5\u03bd\u03cc\u03bc\u03b5\u03bd\u03bf \u03c3\u03b5 \u03bc\u03b1\u03b8\u03b7\u03c4\u03ad\u03c2 \u0394\u03b5\u03c5\u03c4\u03b5\u03c1\u03bf\u03b2\u03ac\u03b8\u03bc\u03b9\u03b1\u03c2 \u0395\u03ba\u03c0\u03b1\u03af\u03b4\u03b5\u03c5\u03c3\u03b7\u03c2.", "level_of_interest": "European, global, national, regional/local", "organisation_name": "AIKATERINI AMOUTZIA (AENAO)", "belgium_office_post_code": "", "number_of_persons_involved": "5", "person_in_charge_of_eu_relations": "AIKATERINI AMOUTZIA", "section": "III - Non-governmental organisations", "source": "", "subsection": "Non-governmental organisations, platforms and networks and similar", "belgium_office_phone": "", "overall_budget_turnover_as_a_range": "", "belgium_office_address": "", "no_geo_reference": true, "persons_accredited_for_access_to_european_parliament_premises": "", "registration_date": "20/04/2011", "estimate_of_costs_absolute_amount": "", "website_address": "http://www.aenao.org", "commission_expert_groups_and_other_similar_entities_european_commission": "NA", "head_office_post_box": "", "head_office_city": "THESSALONIKI", "membership": "Aenao is an active member of the INGO Healthy Network. The Healthy Network is an iNGO, which is an international network that aims at developing partnerships and projects between non-profit organizations and institutions working with young people.  \n \nIt is also active member of the AnaLindh foundation , (www.annalindhfoundation.org)", "head_office_post_code": "57001", "position": "Manager", "financial_year_start_date": "01/01/2017", "head_office_country": "Greece", "number_of_ep_accredited_persons": "", "relevant_communication": "\u03a4\u03b1 \u03b1\u03c0\u03bf\u03c4\u03b5\u03bb\u03ad\u03c3\u03bc\u03b1\u03c4\u03b1 \u03c4\u03c9\u03bd \u03c0\u03c1\u03bf\u03b3\u03c1\u03b1\u03bc\u03bc\u03ac\u03c4\u03c9\u03bd \u0395+  \u03b8\u03b1 \u03c0\u03c1\u03bf\u03c9\u03b8\u03b7\u03b8\u03bf\u03cd\u03bd  \u03c3\u03c4\u03bf dissemination platform , \u03b3\u03b9\u03b1 \u03bd\u03b1 \u03b5\u03af\u03bd\u03b1\u03b9 \u03ac\u03bc\u03b5\u03c3\u03b1 \u03b4\u03b9\u03b1\u03b8\u03ad\u03c3\u03b9\u03bc\u03b1 \u03b3\u03b9\u03b1 \u03ba\u03ac\u03b8\u03b5 \u03b5\u03bd\u03b4\u03b9\u03b1\u03c6\u03b5\u03c1\u03cc\u03bc\u03b5\u03bd\u03bf. \u03ba\u03b1\u03b9  \u03c3\u03c4\u03bf site \u03c4\u03b7\u03c2 \u03bf\u03c1\u03b3\u03ac\u03bd\u03c9\u03c3\u03b7\u03c2", "financial_year_end_date": "01/12/2017", "estimate_of_costs_as_a_range": "25000-49999", "overall_budget_turnover_absolute_amount": "91676", "legal_status": "Non Governmental Organization", "procurement": "", "customers": "", "belgium_office_post_box": "", "goals__remit": "The N.G.O Aenao was established in 2006 in order to promote health, in its wide sense, and to encourage the dialogue between science, culture and religion. It occupies a group of scientists- volunteers, and is coordinated by experienced scientists.  \n \nAenao aims to: \n \n\u2022 Promote health by creating networks and implementing projects based on non-formal education and learning by experience methodology \n \n\u2022 Develop the consciousness of community of health \n \n\u2022 Inform the community on issues regarding science in the broad sense, culture, religion and education \n \n\u2022 Undertake national and international collaboration with reliable agents, in order to exchange experience and best practices \n \n\u2022 Design programs that encourage social cohesion, protect the human rights and respect the environment \n \n\u2022 Empower women to take initiatives and improve their socio-economic status \n \n\u2022 Empower young people, enhance and build their personal skills. \n \n\u2022 Inform society on innovative programs and activities which are consistent with the organization\u2019s aims and disseminate their results through conferences, seminars, meetings, etc. \n \n\u2022 Organize campaigns and initiatives that benefit the society \n \nAenao\u2019s educational material in the field of health promotion has been recognized by the national educational authorities and has been recommended for the school curriculum. \n \nAenao is an active member of the INGO Healthy Network.", "belgium_office_city": "", "head_office_phone": "(+0030)2310420489"}