{"member_organisations": "N.v.t.", "identification_number": "902768024251-21", "fields_of_interest": "Banking and financial services, Fraud prevention", "head_office_address": "Fascinatio Boulevard 1302 2909 VA CAPELLE a/d IJSSEL", "full_time_equivalent_fte": "0,25", "person_with_legal_responsibility": "Aldo Tognini", "financial_year_start_date": "01/01/2017", "grants": "", "country_code": "NL", "head_office_country": "Netherlands", "eu_initiatives": "Blauwtrust Groep en haar entiteiten ondernemen conform de financi\u00eble wetgeving in Nederland.", "level_of_interest": "national", "organisation_name": "Blauwtrust Groep B.V.", "belgium_office_post_code": "", "procurement": "", "section": "II - In-house lobbyists and trade/business/professional associations", "lon": 4.5434272, "source": "", "belgium_office_address": "", "belgium_office_phone": "", "number_of_ep_accredited_persons": "", "overall_budget_turnover_as_a_range": "", "subsection": "Companies & groups", "no_geo_reference": true, "persons_accredited_for_access_to_european_parliament_premises": "", "estimate_of_costs_absolute_amount": "500", "registration_date": "02/11/2016", "website_address": "http://blauwtrustgroep.com", "commission_expert_groups_and_other_similar_entities_european_commission": "NA", "head_office_post_box": "280", "head_office_city": "ROTTERDAM", "membership": "N.v.t.", "head_office_post_code": "3000 AG", "goals__remit": "Blauwtrust Groep connects the housing related supply and demand for residential mortgage funding in the Netherlands through it's entities De Hypotheker, Hypotrust, Quion and Dutch Mortgage Portfolio Management (DMPM). \n \nWith 30+ years of experience the Blauwtrust Groep has built up a solid position in the Dutch residential mortgage market by providing consumers, intermediaries and investors with high quality products and services. Each individual Blauwtrust Groep company provides their customers with best in class propositions, aiming for the highest customer satisfaction. \n \nAt the same time the sum of the Blauwtrust Groep entities provides a full offering from consumer to investor which, from within one independent group, is unique in the Netherlands. This allows us to provide investors with a 'one stop shop' entry to the Dutch residential mortgage market and to provide intermediaries and consumers with high quality mortgage products and services.", "industry_forums": "", "inter_groups": "", "number_of_persons_involved": "1", "relevant_communication": "Geen", "financial_year_end_date": "01/12/2017", "lat": 51.9190494, "estimate_of_costs_as_a_range": "", "overall_budget_turnover_absolute_amount": "0", "legal_status": "B.V.", "person_in_charge_of_eu_relations": "Aldo Tognini", "customers": "", "belgium_office_post_box": "", "position": "waarnemend CEO", "belgium_office_city": "", "head_office_phone": "(+31)102421650"}