{"member_organisations": "", "identification_number": "910203414533-54", "fields_of_interest": "Education and training, Research and innovation", "head_office_address": "Emil-Abderhalden-Stra\u00dfe  37", "full_time_equivalent_fte": "1,75", "person_with_legal_responsibility": "Beate Wagner", "inter_groups": "", "financial_year_start_date": "01/01/2017", "grants": "", "head_office_country": "Germany", "eu_initiatives": "Horizon 2020", "organisation_name": "Global Young Academy (GYA)", "belgium_office_post_code": "", "number_of_persons_involved": "5", "procurement": "", "section": "IV - Think tanks, research and academic institutions", "source": "", "belgium_office_address": "", "subsection": "Think tanks and research institutions", "belgium_office_phone": "", "number_of_ep_accredited_persons": "", "overall_budget_turnover_as_a_range": "", "belgium_office_city": "", "persons_accredited_for_access_to_european_parliament_premises": "", "estimate_of_costs_absolute_amount": "", "registration_date": "29/09/2014", "website_address": "http://www.globalyoungacademy.net", "commission_expert_groups_and_other_similar_entities_european_commission": "Open Science Policy Platform#E03436#http://ec.europa.eu/transparency/regexpert/index.cfm?do=groupDetail.groupDetail&groupID=3436#Member#C", "head_office_post_box": "", "head_office_city": "Halle (Saale)", "membership": "The GYA has observer status at the IAP - The Global Network of Science Academies.", "head_office_post_code": "06108", "goals__remit": "As the \u201cvoice of young scientists around the world\u201d the Global Young Academy (GYA) aims to empower and mobilize young scientists in their creative prime to address issues of particular importance to early career scientists and to advance science-society and science-policy dialogues. The GYA is an international organization that bridges the gap between the developing and the developed worlds, helping to make science around the world more effective in the discovery of new knowledge and its communication to society. \n \nIn its activities, the GYA focuses on: \n\u2022    Supporting young scientists in career development and independence  \n\u2022    Promoting interdisciplinary, international, and intergenerational dialogue on scientific issues \n\u2022    Encouraging novel, scientific approaches to solve problems of international significance \n\u2022    Building capacity for science in the developing world \n\u2022    Developing science education and communication to encourage science as a career choice and for more effective, evidence-based decision-making \n\u2022    Supporting the development and cooperation of National Young Academies.", "industry_forums": "", "head_office_phone": "(+49)34547239170", "level_of_interest": "global", "relevant_communication": "project with the JRC in preparation", "financial_year_end_date": "01/12/2017", "estimate_of_costs_as_a_range": "100000-199999", "overall_budget_turnover_absolute_amount": "550723", "legal_status": "Projekt der Nationalen Akademie der Wissenschaften, Leopoldina gemeinn\u00fctziger eingetragener Verein", "person_in_charge_of_eu_relations": "Beate Wagner", "customers": "", "belgium_office_post_box": "", "position": "Managing Director"}