{"member_organisations": "", "identification_number": "917980810335-45", "fields_of_interest": "Agriculture, Research and innovation, Trans-European Networks, Food Safety, Climate Action", "head_office_address": "K\u00f6lsumer Weg 33", "full_time_equivalent_fte": "0,25", "person_with_legal_responsibility": "Peter Welters", "inter_groups": "", "financial_year_start_date": "01/01/2016", "grants": "0", "head_office_country": "Germany", "eu_initiatives": "JU-BBI", "organisation_name": "Phytowelt GreenTechnologies GmbH (PHYTOWELT)", "belgium_office_post_code": "", "number_of_persons_involved": "1", "procurement": "0", "section": "II - In-house lobbyists and trade/business/professional associations", "source": "-", "belgium_office_address": "", "subsection": "Companies & groups", "belgium_office_phone": "", "number_of_ep_accredited_persons": "", "overall_budget_turnover_as_a_range": "", "belgium_office_city": "", "persons_accredited_for_access_to_european_parliament_premises": "", "estimate_of_costs_absolute_amount": "", "registration_date": "14/12/2012", "website_address": "http://www.phytowelt.com", "commission_expert_groups_and_other_similar_entities_european_commission": "NA", "head_office_post_box": "", "head_office_city": "Nettetal", "membership": "CLIB2021, Germany \nCleanTechNRW, Germany \nABIC Foundation, Canada \nDeutsche Industrievereinigung Biotechnologie (DIB), Germany \nDECHEMA, Germany \nBIC (JU-BBI) \nGemeinschaft zur F\u00f6rderung von Pflanzeninnovation e. V. (GFPi), Germany", "head_office_post_code": "41334", "goals__remit": "Phytowelt GreenTechnologies GmbH is an internationally operating R&D company with core competences in industrial and plant biotechnology. Our services and process developments build a bridge between white and green biotechnology and tap the potential of plant biodiversity for the introduction of sustainable, industrial production processes using renewable raw materials. \n \nThe knowledge of plant secondary metabolites, their biosynthesis pathways and the enzymes involved, in combination with unique solutions to produce those metabolites and enzymes in micro organisms, is our key to success. Supplemented by the expertise to improve the breeding of plants by means of double haploids and protoplast fusion, this produces better renewable raw materials for bioenergy and biomaterials. With its expertise Phytowelt provides to its customers the best solution for a green, clean and sustainable production.", "industry_forums": "", "head_office_phone": "(+49)2162 77859", "level_of_interest": "global", "relevant_communication": "", "financial_year_end_date": "01/12/2016", "estimate_of_costs_as_a_range": "0-9999", "overall_budget_turnover_absolute_amount": "0", "legal_status": "SME", "person_in_charge_of_eu_relations": "Peter Welters", "customers": "", "belgium_office_post_box": "", "position": "CEO"}