{"member_organisations": "", "identification_number": "930012124180-38", "fields_of_interest": "Agriculture, Energy, Business and Industry, Environment, Maritime affairs and fisheries, Research and innovation, Food Safety", "head_office_address": "VIALE TANARA, 31/A", "full_time_equivalent_fte": "3,5", "person_with_legal_responsibility": "ANDREA ZANLARI", "industry_forums": "", "grants": "", "country_code": "it", "inter_groups": "", "eu_initiatives": "Attivit\u00e0 di ricerca nel settore agro alimentare, inserita in progetti di ricerca", "level_of_interest": "European", "organisation_name": "STAZIONE SPERIMENTALE PER L'INDUSTRIA DELLE CONSERVE ALIMENTARI (SSICA)", "belgium_office_post_code": "", "number_of_persons_involved": "7", "person_in_charge_of_eu_relations": "ANNA MARIA GUERRA", "section": "IV - Think tanks, research and academic institutions", "lon": "10.1816266", "source": "", "subsection": "Think tanks and research institutions", "belgium_office_phone": "", "overall_budget_turnover_as_a_range": "", "belgium_office_address": "", "persons_accredited_for_access_to_european_parliament_premises": "", "registration_date": "28/10/2016", "estimate_of_costs_absolute_amount": "0", "website_address": "http://www.ssica.it", "commission_expert_groups_and_other_similar_entities_european_commission": "NA", "head_office_post_box": "", "head_office_city": "PARMA", "membership": "", "head_office_post_code": "43121", "position": "RESPONSABILE RISORSE UMANE E AMMINSTRAZIONE", "financial_year_start_date": "", "head_office_country": "Italy", "number_of_ep_accredited_persons": "", "relevant_communication": "Progetto BIOCOPAC LIFE \npROGETTI REGIONALI \nCIBUS \nCIBUSTEC", "financial_year_end_date": "", "lat": "44.8130651", "estimate_of_costs_as_a_range": "", "overall_budget_turnover_absolute_amount": "0", "legal_status": "FONDAZIONE DI RICERCA", "procurement": "", "customers": "", "belgium_office_post_box": "", "goals__remit": "La SSICA promuove il progresso tecnico e tecnologico dell'Industria Conserviera. La SSICA svolge attivit\u00e0 di ricerca, consulenza, analisi, formazione e divulgazione, propone l'attivazione di progetti di ricerca, fornisce risposte ai problemi dell'Industria  conserviera per migliorare gli standard qualitativi e sicurezza. La struttura \u00e8 dotata di dipartimenti specialistici per i diversi settori merceologici, nonch\u00e9 di dipartimenti e laboratori multidisciplinari e dispone di apparecchiature e competenze volte a sperimentare anche nuovi prodotti e nuovi processi di trasformazione e conservazione, inclusi i materiali e le nuove tecniche di confezionamento e imballaggio.", "belgium_office_city": "", "head_office_phone": "(+39)05217951"}